[
  {"id": 1, "rating": 2, "comment": "배송이 너무 느려요. 일주일이나 걸렸네요.", "timestamp": "2026-02-15T10:00:00Z", "language": "ko"},
  {"id": 2, "rating": 5, "comment": "커피 맛이 정말 일품입니다. 시그니처 라떼 최고!", "timestamp": "2026-02-15T11:30:00Z", "language": "ko"},
  {"id": 3, "rating": 1, "comment": "포장이 다 터져서 왔어요. 내용물이 다 샜네요. 환불해주세요.", "timestamp": "2026-02-15T14:20:00Z", "language": "ko"},
  {"id": 4, "rating": 4, "comment": "매장이 깔끔하고 직원분들이 친절해서 기분 좋게 이용했습니다.", "timestamp": "2026-02-16T09:15:00Z", "language": "ko"},
  {"id": 5, "rating": 3, "comment": "맛은 있는데 가격이 좀 비싼 느낌이 드네요.", "timestamp": "2026-02-16T12:00:00Z", "language": "ko"},
  {"id": 6, "rating": 2, "comment": "택배사가 문제인 건지 배송 상태가 엉망입니다. 박스가 젖어있었어요.", "timestamp": "2026-02-16T15:45:00Z", "language": "ko"},
  {"id": 7, "rating": 5, "comment": "선물용으로 샀는데 받는 분이 너무 좋아하시네요. 재구매 의사 100%!", "timestamp": "2026-02-17T08:30:00Z", "language": "ko"},
  {"id": 8, "rating": 2, "comment": "주말에 갔는데 대기가 너무 길어요. 주문하고 30분 넘게 기다렸습니다.", "timestamp": "2026-02-17T13:10:00Z", "language": "ko"},
  {"id": 9, "rating": 4, "comment": "디저트가 다양해서 골라 먹는 재미가 있네요. 다 맛있어요.", "timestamp": "2026-02-17T16:20:00Z", "language": "ko"},
  {"id": 10, "rating": 1, "comment": "배송 지연이 너무 심각합니다. 고객센터는 연결도 안 되고 답답하네요.", "timestamp": "2026-02-18T10:05:00Z", "language": "ko"},
  {"id": 11, "rating": 5, "comment": "The atmosphere is great and the coffee is authentic.", "timestamp": "2026-02-18T11:50:00Z", "language": "en"},
  {"id": 12, "rating": 2, "comment": "맛은 평범한데 양이 너무 적어요. 실망입니다.", "timestamp": "2026-02-18T14:40:00Z", "language": "ko"},
  {"id": 13, "rating": 4, "comment": "주차가 조금 힘들긴 하지만 커피 마시러 올 가치가 충분합니다.", "timestamp": "2026-02-19T09:00:00Z", "language": "ko"},
  {"id": 14, "rating": 1, "comment": "화장실이 너무 지저분해요. 매장 관리에 더 신경 써야 할 듯.", "timestamp": "2026-02-19T12:30:00Z", "language": "ko"},
  {"id": 15, "rating": 5, "comment": "항상 믿고 먹는 곳입니다. 배송도 이 정도면 만족해요.", "timestamp": "2026-02-19T15:10:00Z", "language": "ko"},
  {"id": 16, "rating": 2, "comment": "OO택배사 배송이 너무 느립니다. 지역마다 차이가 있겠지만 저희 동네는 최악이에요.", "timestamp": "2026-02-20T10:20:00Z", "language": "ko"},
  {"id": 17, "rating": 3, "comment": "보통입니다. 특별한 건 없어요.", "timestamp": "2026-02-20T13:00:00Z", "language": "ko"},
  {"id": 18, "rating": 4, "comment": "인테리어가 예뻐서 사진 찍기 좋네요. 인스타 감성 가득!", "timestamp": "2026-02-20T16:45:00Z", "language": "ko"},
  {"id": 19, "rating": 1, "comment": "주문한 메뉴랑 다른 게 나왔어요. 대처도 미흡해서 기분 상했네요.", "timestamp": "2026-02-21T09:30:00Z", "language": "ko"},
  {"id": 20, "rating": 5, "comment": "Best coffee in town! Highly recommended.", "timestamp": "2026-02-21T11:00:00Z", "language": "en"},
  {"id": 21, "rating": 2, "comment": "커피는 맛있는데 음악 소리가 너무 커서 대화하기 힘들어요.", "timestamp": "2026-02-21T14:15:00Z", "language": "ko"},
  {"id": 22, "rating": 4, "comment": "선물용 패키지가 고급스러워요. 받는 사람이 좋아했어요.", "timestamp": "2026-02-22T10:00:00Z", "language": "ko"},
  {"id": 23, "rating": 1, "comment": "배송받았는데 유리병이 깨져서 왔습니다. 위험할 뻔했네요.", "timestamp": "2026-02-22T13:40:00Z", "language": "ko"},
  {"id": 24, "rating": 3, "comment": "쏘쏘합니다. 재방문은 고민해 봐야겠어요.", "timestamp": "2026-02-22T16:20:00Z", "language": "ko"},
  {"id": 25, "rating": 5, "comment": "친절한 서비스에 감동받았습니다. 단골 될 것 같아요!", "timestamp": "2026-02-23T09:10:00Z", "language": "ko"},
  {"id": 26, "rating": 2, "comment": "배송 알림도 없이 집 앞에 그냥 두고 갔네요. 분실될 뻔했습니다.", "timestamp": "2026-02-23T12:05:00Z", "language": "ko"},
  {"id": 27, "rating": 4, "comment": "다양한 원두를 고를 수 있어서 좋았습니다.", "timestamp": "2026-02-23T15:30:00Z", "language": "ko"},
  {"id": 28, "rating": 1, "comment": "커피에서 탄 맛이 너무 강하게 나요. 원두가 탄 건지 추출이 잘못된 건지.", "timestamp": "2026-02-24T10:50:00Z", "language": "ko"},
  {"id": 29, "rating": 5, "comment": "매일 마셔도 안 질리는 맛입니다. 정기 배송 신청했어요.", "timestamp": "2026-02-24T13:20:00Z", "language": "ko"},
  {"id": 30, "rating": 2, "comment": "택배사 좀 바꿔주세요. 배송 지연 때문에 신선도가 떨어지는 것 같아요.", "timestamp": "2026-02-24T16:00:00Z", "language": "ko"},
  {"id": 31, "rating": 4, "comment": "아늑한 분위기가 좋아서 혼자 작업하기 좋습니다.", "timestamp": "2026-02-25T09:40:00Z", "language": "ko"},
  {"id": 32, "rating": 1, "comment": "불친절의 끝판왕. 다시는 안 갑니다.", "timestamp": "2026-02-25T12:15:00Z", "language": "ko"},
  {"id": 33, "rating": 3, "comment": "괜찮긴 한데 줄 서서 먹을 정도는 아닌 듯.", "timestamp": "2026-02-25T15:00:00Z", "language": "ko"},
  {"id": 34, "rating": 5, "comment": "Lovely place with great staff!", "timestamp": "2026-02-26T10:10:00Z", "language": "en"},
  {"id": 35, "rating": 2, "comment": "포장지가 너무 과한 것 같아요. 환경 생각 좀 해주세요.", "timestamp": "2026-02-26T13:45:00Z", "language": "ko"},
  {"id": 36, "rating": 4, "comment": "아이들이랑 오기에도 좋네요. 키즈 메뉴가 생겼으면 좋겠어요.", "timestamp": "2026-02-26T16:30:00Z", "language": "ko"},
  {"id": 37, "rating": 1, "comment": "곰팡이가 핀 것 같아요. 위생 상태 점검 필수인 듯 합니다.", "timestamp": "2026-02-27T09:20:00Z", "language": "ko"},
  {"id": 38, "rating": 5, "comment": "주변에 소문 많이 내고 있어요. 번창하세요!", "timestamp": "2026-02-27T12:00:00Z", "language": "ko"},
  {"id": 39, "rating": 2, "comment": "배송 지연 공지가 미리 있었으면 좋았을 텐데 아쉽네요.", "timestamp": "2026-02-27T15:10:00Z", "language": "ko"},
  {"id": 40, "rating": 4, "comment": "쿠폰 혜택이 쏠쏠하네요. 자주 이용할게요.", "timestamp": "2026-02-28T10:05:00Z", "language": "ko"},
  {"id": 41, "rating": 1, "comment": "얼음이 너무 많아서 커피 양이 너무 적어요. 몇 모금 마시니 끝.", "timestamp": "2026-02-28T13:30:00Z", "language": "ko"},
  {"id": 42, "rating": 5, "comment": "Great value for the price.", "timestamp": "2026-02-28T16:15:00Z", "language": "en"},
  {"id": 43, "rating": 2, "comment": "제품은 좋은데 박스 테이프 처리가 허술해서 박스가 열려 있었어요.", "timestamp": "2026-03-01T11:00:00Z", "language": "ko"},
  {"id": 44, "rating": 4, "comment": "새로 나온 신메뉴 너무 맛있어요! 꼭 드셔보세요.", "timestamp": "2026-03-01T14:20:00Z", "language": "ko"},
  {"id": 45, "rating": 1, "comment": "택배사 파업 때문이라지만 너무 늦네요. 미리 알려주셨어야죠.", "timestamp": "2026-03-01T17:05:00Z", "language": "ko"},
  {"id": 46, "rating": 5, "comment": "배송 상태 매우 양호합니다. 꼼꼼한 포장 감사해요.", "timestamp": "2026-03-02T10:30:00Z", "language": "ko"},
  {"id": 47, "rating": 2, "comment": "맛이 예전만 못하네요. 변한 것 같아 아쉽습니다.", "timestamp": "2026-03-02T13:45:00Z", "language": "ko"},
  {"id": 48, "rating": 4, "comment": "가족 모임 장소로 추천합니다. 넓고 쾌적해요.", "timestamp": "2026-03-02T16:20:00Z", "language": "ko"},
  {"id": 49, "rating": 1, "comment": "머리카락이 나왔어요... 입맛 뚝 떨어졌습니다.", "timestamp": "2026-03-03T09:50:00Z", "language": "ko"},
  {"id": 50, "rating": 5, "comment": "Best experience ever. Will come back for sure.", "timestamp": "2026-03-03T12:15:00Z", "language": "en"}
]
